gadgetpy/__init__.py
gadgetpy/config.py
gadgetpy/error.py
gadgetpy/function.py
gadgetpy/gadget.py
gadgetpy/utils.py
gadgetpy-0.2.dist-info/METADATA
gadgetpy-0.2.dist-info/WHEEL
gadgetpy-0.2.dist-info/top_level.txt
gadgetpy-0.2.dist-info/RECORD
