Metadata-Version: 2.1
Name: gadgetpy
Version: 0.2
Summary: Manage USB_Gadget devices in ConfigFS
Home-page: http://github.com/projectmakeit/gadgetpy
Author: Blixa Morgan (MrMakeIt)
Author-email: blixa@projectmakeit.com
License: MIT
Platform: UNKNOWN
